xontrib/ranger.py
xontrib_ranger-0.0.1.dist-info/WHEEL
xontrib_ranger-0.0.1.dist-info/METADATA
xontrib_ranger-0.0.1.dist-info/licenses/LICENSE
xontrib_ranger-0.0.1.dist-info/RECORD
