Metadata-Version: 2.1
Name: xontrib-ranger
Version: 0.0.1
Summary: ranger integration for xonsh shell
License: MIT
Keywords: xontrib,xonsh,ranger
Author-email: Jez Cope <j.cope@erambler.co.uk>
Requires-Python: >=3.7
Classifier: Intended Audience :: Developers
Classifier: License :: OSI Approved :: MIT License
Classifier: Natural Language :: English
Classifier: Operating System :: OS Independent
Classifier: Programming Language :: Python
Classifier: Programming Language :: Python :: 3
Classifier: Programming Language :: Python :: 3.6
Classifier: Programming Language :: Python :: 3.7
Classifier: Programming Language :: Python :: 3.8
Classifier: Topic :: System :: Shells
Classifier: Topic :: System :: System Shells
Classifier: Topic :: Terminals
Requires-Dist: xonsh>=0.12
Provides-Extra: dev
Requires-Dist: pytest; extra == "dev"
Requires-Dist: black; extra == "dev"
Project-URL: Code, https://github.com/jezcope/xontrib-ranger
Project-URL: Documentation, https://github.com/jezcope/xontrib-ranger/blob/master/README.md
Project-URL: Issue tracker, https://github.com/jezcope/xontrib-ranger/issues
Project-URL: repository, https://github.com/jezcope/xontrib-ranger
